[
  {
    "args": ["ARRANGE table:x AS y USING invert();"],
    "expects": {
      "steps" : [
        {
          "name" : "arrange",
          "table" : { "type" : "reference", "section" : "table", "key" : "x" },
          "table_name" : "y",
          "arrangements" : [
            {
              "type" : "function",
              "name" : "invert",
              "args" : []
            }
          ]
        }
      ]
    }
  },
  {
    "args": ["ARRANGE table:x AS y USING shift(2);"],
    "expects": {
      "steps" : [
        {
          "name" : "arrange",
          "table" : { "type" : "reference", "section" : "table", "key" : "x" },
          "table_name" : "y",
          "arrangements" : [
            {
              "type" : "function",
              "name" : "shift",
              "args" : [
                { "type" : "number", "value" : "2" }
              ]
            }
          ]
        }
      ]
    }
  },
  {
    "args": ["ARRANGE table:x AS y USING shift(-2) USING invert();"],
    "expects": {
      "steps" : [
        {
          "name" : "arrange",
          "table" : { "type" : "reference", "section" : "table", "key" : "x" },
          "table_name" : "y",
          "arrangements" : [
            {
              "type" : "function",
              "name" : "shift",
              "args" : [
                { "type" : "number", "value" : "-2" }
              ]
            },
            {
              "type" : "function",
              "name" : "invert",
              "args" : []
            }
          ]
        }
      ]
    }
  },
  {
    "args": ["ARRANGE table:x AS y USING sort(a, \"alpha\", \"descending\");"],
    "expects": {
      "steps" : [
        {
          "name" : "arrange",
          "table" : { "type" : "reference", "section" : "table", "key" : "x" },
          "table_name" : "y",
          "arrangements" : [
            {
              "type" : "function",
              "name" : "sort",
              "args" : [
                { "type" : "reference", "section" : "_column", "key" : "a" },
                { "type" : "string", "value" : "alpha" },
                { "type" : "string", "value" : "descending" }
              ]
            }
          ]
        }
      ]
    }
  }
]
